[
  {
    "epoch": 1,
    "stage": "head",
    "train_loss": 1.9228371279580252,
    "train_accuracy": 25.0,
    "val_loss": 1.6068636576334636,
    "val_accuracy": 20.0,
    "learning_rate": 0.001
  },
  {
    "epoch": 2,
    "stage": "head",
    "train_loss": 1.6383384943008423,
    "train_accuracy": 23.214285714285715,
    "val_loss": 1.5046270158555772,
    "val_accuracy": 32.857142857142854,
    "learning_rate": 0.001
  },
  {
    "epoch": 3,
    "stage": "head",
    "train_loss": 1.5629662786211287,
    "train_accuracy": 28.928571428571427,
    "val_loss": 1.5035187668270535,
    "val_accuracy": 28.571428571428573,
    "learning_rate": 0.001
  },
  {
    "epoch": 4,
    "stage": "head",
    "train_loss": 1.5661637680871145,
    "train_accuracy": 27.857142857142858,
    "val_loss": 1.504989915423923,
    "val_accuracy": 40.0,
    "learning_rate": 0.001
  },
  {
    "epoch": 5,
    "stage": "head",
    "train_loss": 1.498960144179208,
    "train_accuracy": 29.642857142857142,
    "val_loss": 1.4476347896787856,
    "val_accuracy": 44.285714285714285,
    "learning_rate": 0.001
  },
  {
    "epoch": 6,
    "stage": "layer4",
    "train_loss": 1.512618088722229,
    "train_accuracy": 29.642857142857142,
    "val_loss": 1.3670350048277113,
    "val_accuracy": 47.142857142857146,
    "learning_rate": 0.0001
  },
  {
    "epoch": 8,
    "stage": "layer4",
    "train_loss": 1.526311925479344,
    "train_accuracy": 29.285714285714285,
    "val_loss": 1.3466551568773057,
    "val_accuracy": 50.0,
    "learning_rate": 0.0001
  },
  {
    "epoch": 10,
    "stage": "layer4",
    "train_loss": 1.4588335514068604,
    "train_accuracy": 31.785714285714285,
    "val_loss": 1.3767979145050049,
    "val_accuracy": 42.857142857142854,
    "learning_rate": 0.0001
  },
  {
    "epoch": 12,
    "stage": "layer4",
    "train_loss": 1.4510957649775913,
    "train_accuracy": 35.0,
    "val_loss": 1.264251920912001,
    "val_accuracy": 54.285714285714285,
    "learning_rate": 0.0001
  },
  {
    "epoch": 14,
    "stage": "layer4",
    "train_loss": 1.3607695852007184,
    "train_accuracy": 37.5,
    "val_loss": 1.3292678727044,
    "val_accuracy": 45.714285714285715,
    "learning_rate": 0.0001
  },
  {
    "epoch": 11,
    "stage": "deep",
    "train_loss": 1.317445751598903,
    "train_accuracy": 40.0,
    "val_loss": 1.1899389227231343,
    "val_accuracy": 48.57142857142857,
    "learning_rate": 1e-05
  },
  {
    "epoch": 13,
    "stage": "deep",
    "train_loss": 1.3123700397355216,
    "train_accuracy": 41.42857142857143,
    "val_loss": 1.143913937939538,
    "val_accuracy": 61.42857142857143,
    "learning_rate": 1e-05
  },
  {
    "epoch": 15,
    "stage": "deep",
    "train_loss": 1.2934530326298306,
    "train_accuracy": 44.642857142857146,
    "val_loss": 1.1488548583454556,
    "val_accuracy": 60.0,
    "learning_rate": 1e-05
  },
  {
    "epoch": 17,
    "stage": "deep",
    "train_loss": 1.266811067717416,
    "train_accuracy": 45.714285714285715,
    "val_loss": 1.159114850891961,
    "val_accuracy": 57.142857142857146,
    "learning_rate": 1e-05
  },
  {
    "epoch": 19,
    "stage": "deep",
    "train_loss": 1.2589884264128548,
    "train_accuracy": 44.642857142857146,
    "val_loss": 1.1633462574746873,
    "val_accuracy": 50.0,
    "learning_rate": 1e-05
  }
]